vutil/__init__.py
vutil/_nbdev.py
vutil/imports.py
vutil/pprint.py
vutil-0.0.3.dist-info/LICENSE
vutil-0.0.3.dist-info/METADATA
vutil-0.0.3.dist-info/WHEEL
vutil-0.0.3.dist-info/entry_points.txt
vutil-0.0.3.dist-info/top_level.txt
vutil-0.0.3.dist-info/RECORD
