Metadata-Version: 2.1
Name: vutil
Version: 0.0.3
Summary: Some python utilities
Home-page: https://github.com/civvic/vutil/tree/master/
Author: civvic
Author-email: civvic@gmail.com
License: Apache Software License 2.0
Keywords: python util
Platform: UNKNOWN
Classifier: Development Status :: 3 - Alpha
Classifier: Intended Audience :: Developers
Classifier: License :: OSI Approved :: Apache Software License
Classifier: Natural Language :: English
Classifier: Programming Language :: Python :: 3.6
Classifier: Programming Language :: Python :: 3.7
Classifier: Programming Language :: Python :: 3.8
Requires-Python: >=3.6
